pyjson5x/__init__.py
pyjson5x/pyjson5x.pypy39-pp73-x86_64-linux-gnu.so
pyjson5x/py.typed
pyjson5x/__init__.pyi
pyjson5x-1.6.2.1.dist-info/RECORD
pyjson5x-1.6.2.1.dist-info/METADATA
pyjson5x-1.6.2.1.dist-info/LICENSE
pyjson5x-1.6.2.1.dist-info/top_level.txt
pyjson5x-1.6.2.1.dist-info/WHEEL
